{"format_version":"0.6.1","tag":"0.0.3","formatted_date":"Sep  6 2024 at 14:05 UTC","platforms_with_downloads":[{"target":["aarch64-apple-darwin"],"display_name":"macOS Apple Silicon","installers":[1]},{"target":["x86_64-apple-darwin"],"display_name":"macOS Intel","installers":[1]},{"target":["x86_64-unknown-linux-gnu"],"display_name":"Linux x64","installers":[1,0]}],"downloadable_files":[[2,{"name":"pnafs-x86_64-unknown-linux-gnu.tar.xz","download_url":"https://github.com/Portable-Network-Archive/fs/releases/download/0.0.3/pnafs-x86_64-unknown-linux-gnu.tar.xz","view_path":null,"checksum_file":3},["Linux x64"]]],"release":{"artifacts":{"files":[{"name":"dist-manifest.json","download_url":"https://github.com/Portable-Network-Archive/fs/releases/download/0.0.3/dist-manifest.json","view_path":null,"checksum_file":null},{"name":"pnafs-installer.sh","download_url":"https://github.com/Portable-Network-Archive/fs/releases/download/0.0.3/pnafs-installer.sh","view_path":"pnafs-installer.sh.txt","checksum_file":null},{"name":"pnafs-x86_64-unknown-linux-gnu.tar.xz","download_url":"https://github.com/Portable-Network-Archive/fs/releases/download/0.0.3/pnafs-x86_64-unknown-linux-gnu.tar.xz","view_path":null,"checksum_file":3},{"name":"pnafs-x86_64-unknown-linux-gnu.tar.xz.sha256","download_url":"https://github.com/Portable-Network-Archive/fs/releases/download/0.0.3/pnafs-x86_64-unknown-linux-gnu.tar.xz.sha256","view_path":null,"checksum_file":null},{"name":"source.tar.gz","download_url":"https://github.com/Portable-Network-Archive/fs/releases/download/0.0.3/source.tar.gz","view_path":null,"checksum_file":5},{"name":"source.tar.gz.sha256","download_url":"https://github.com/Portable-Network-Archive/fs/releases/download/0.0.3/source.tar.gz.sha256","view_path":null,"checksum_file":null}],"installers":[{"label":"tarball","description":"","app_name":null,"method":{"type":"Download","file":2}},{"label":"shell","description":"","app_name":null,"method":{"type":"Run","file":1,"run_hint":"curl --proto '=https' --tlsv1.2 -LsSf https://github.com/Portable-Network-Archive/fs/releases/download/0.0.3/pnafs-installer.sh | sh"}}],"targets":{"aarch64-apple-darwin":[1],"aarch64-unknown-linux-gnu":[1],"aarch64-unknown-linux-musl":[1],"i686-apple-darwin":[1],"i686-unknown-linux-gnu":[1],"i686-unknown-linux-musl":[1],"x86_64-apple-darwin":[1],"x86_64-unknown-linux-gnu":[1,0],"x86_64-unknown-linux-musl":[1]}}},"os_script":"/fs/artifacts.js","has_checksum_files":true}